{
  "name": "WIN-ED7L7UQSMSC",
  "protocol_version": "1",
  "integration_version": "0.1.0",
  "events": [],
  "inventory": {},
  "metrics": [
    {
      "event_type": "PerfmonMetrics",
      "ASPNETApplications(__Total__).ErrorsTotal": 0.0,
      "ASPNETApplications(__Total__).RequestsPerSec": 0.0,
      "NETCLRExceptions(_Global_).NumberofExcepsThrown": 11979.0,
      "NETCLRExceptions(_Global_).NumberofExcepsThrownPersec": 15.0,
      "NETCLRExceptions(_Global_).NumberofFiltersPersec": 0.0,
      "NETCLRExceptions(_Global_).NumberofFinallysPersec": 0.0,
      "NETCLRExceptions(_Global_).ThrowToCatchDepthPersec": 0.0,
      "NETCLRInterop(_Global_).NumberofCCWs": 4488.0,
      "NETCLRInterop(_Global_).Numberofmarshalling": 0.0,
      "NETCLRInterop(_Global_).NumberofStubs": 7767.0,
      "NETCLRInterop(_Global_).NumberofTLBexportsPersec": 8.0,
      "NETCLRInterop(_Global_).NumberofTLBimportsPersec": 0.0,
      "NETCLRJit(_Global_).ILBytesJittedPersec": 0.0,
      "NETCLRJit(_Global_).NumberofILBytesJitted": 4721595.0,
      "NETCLRJit(_Global_).NumberofMethodsJitted": 58922.0,
      "NETCLRJit(_Global_).PercentTimeinJit": 0.0,
      "NETCLRJit(_Global_).TotalNumberofILBytesJitted": 4721595.0,
      "NETCLRLoading(_Global_).AssemblySearchLength": 0.0,
      "NETCLRLoading(_Global_).BytesinLoaderHeap": 66748416.0,
      "NETCLRLoading(_Global_).Currentappdomains": 10.0,
      "NETCLRLoading(_Global_).CurrentAssemblies": 816.0,
      "NETCLRLoading(_Global_).CurrentClassesLoaded": 41396.0,
      "NETCLRLoading(_Global_).PercentTimeLoading": 0.0,
      "NETCLRLoading(_Global_).TotalAppdomains": 14.0,
      "NETCLRLoading(_Global_).Totalappdomainsunloaded": 4.0,
      "NETCLRLoading(_Global_).TotalAssemblies": 852.0,
      "NETCLRLoading(_Global_).TotalClassesLoaded": 41396.0,
      "NETCLRLoading(_Global_).TotalNumberofLoadFailures": 556.0,
      "NETCLRLocksAndThreads(_Global_).ContentionRatePersec": 7.0,
      "NETCLRLocksAndThreads(_Global_).CurrentQueueLength": 4.0,
      "NETCLRLocksAndThreads(_Global_).NumberofcurrentlogicalThreads": 177.0,
      "NETCLRLocksAndThreads(_Global_).NumberofcurrentphysicalThreads": 155.0,
      "NETCLRLocksAndThreads(_Global_).Numberofcurrentrecognizedthreads": 22.0,
      "NETCLRLocksAndThreads(_Global_).Numberoftotalrecognizedthreads": 80.0,
      "NETCLRLocksAndThreads(_Global_).QueueLengthPersec": 0.0,
      "NETCLRLocksAndThreads(_Global_).TotalNumberofContentions": 4380.0,
      "NETCLRMemory(_Global_).AllocatedBytesPersec": 0.0,
      "NETCLRMemory(_Global_).Gen0heapsize": 55386012.0,
      "NETCLRMemory(_Global_).Gen1heapsize": 2714332.0,
      "NETCLRMemory(_Global_).Gen2heapsize": 160925024.0,
      "NETCLRMemory(_Global_).LargeObjectHeapsize": 11026936.0,
      "NETCLRMemory(_Global_).NumberBytesinallHeaps": 174666304.0,
      "NETCLRMemory(_Global_).NumberInducedGC": 5.0,
      "NETCLRMemory(_Global_).NumberTotalcommittedBytes": 230424576.0,
      "NETCLRMemory(_Global_).NumberTotalreservedBytes": 452907008.0,
      "NETCLRMemory(_Global_).AllocatedBytesPersec#1": 0.0,
      "NETCLRMemory(_Global_).NumberGen0Collections": 3056.0,
      "NETCLRMemory(_Global_).NumberGen1Collections": 1642.0,
      "NETCLRMemory(_Global_).NumberGen2Collections": 174.0,
      "NETCLRMemory(_Global_).PercentTimeinGC": 0.0,
      "ASPNETStateService.StateServerSessionsAbandoned": 0.0,
      "ASPNETStateService.StateServerSessionsActive": 0.0,
      "ASPNETStateService.StateServerSessionsTimedOut": 0.0,
      "ASPNETStateService.StateServerSessionsTotal": 0.0,
      "ASPNET.ApplicationRestarts": 0.0,
      "ASPNET.ApplicationsRunning": 0.0,
      "ASPNET.ErrorEventsRaised": 0.0,
      "ASPNET.InfrastructureErrorEventsRaised": 0.0,
      "ASPNET.RequestErrorEventsRaised": 0.0,
      "ASPNET.RequestExecutionTime": 0.0,
      "ASPNET.RequestsCurrent": 0.0,
      "ASPNET.RequestsQueued": 0.0,
      "ASPNET.RequestsRejected": 0.0,
      "ASPNET.RequestWaitTime": 0.0,
      "ASPNET.WorkerProcessesRunning": 0.0,
      "ASPNET.WorkerProcessRestarts": 0.0,
      "ASPNET.RequestWaitTime#1": 0.0,
      "WebService(_Total).BytesReceivedPersec": 0.0,
      "WebService(_Total).BytesSentPersec": 0.0,
      "WebService(_Total).ConnectionAttemptsPersec": 0.0,
      "WebService(_Total).CurrentConnections": 0.0
    }
  ]
}